axis_reasoning/__init__.py
axis_reasoning/engine.py
axis_reasoning/executor.py
axis_reasoning/model_selector.py
axis_reasoning/_internal/__init__.py
axis_reasoning/_internal/config.py
axis_reasoning/_internal/context7_schemas.py
axis_reasoning/_internal/context_detector.py
axis_reasoning/_internal/decision_logger.py
axis_reasoning/_internal/di.py
axis_reasoning/_internal/epistemology.py
axis_reasoning/_internal/ingestor.py
axis_reasoning/_internal/kill_switch.py
axis_reasoning/_internal/logging.py
axis_reasoning/_internal/observability.py
axis_reasoning/_internal/schemas.py
axis_reasoning/_internal/state_paths.py
axis_reasoning/_internal/telemetry.py
axis_reasoning/_internal/timestamp_contract.py
axis_reasoning/orchestrator/__init__.py
axis_reasoning/orchestrator/context.py
axis_reasoning/orchestrator/context_cache.py
axis_reasoning/orchestrator/feedback_collector.py
axis_reasoning/orchestrator/routing_context.py
axis_reasoning/planner/__init__.py
axis_reasoning/planner/diagnostics.py
axis_reasoning/planner/planner.py
axis_reasoning/runtime/__init__.py
axis_reasoning/runtime/contracts.py
axis_reasoning/runtime/orchestrator_errors.py
axis_reasoning/session/__init__.py
axis_reasoning/session/ledger.py
axis_reasoning-0.1.1.dist-info/METADATA
axis_reasoning-0.1.1.dist-info/WHEEL
axis_reasoning-0.1.1.dist-info/top_level.txt
axis_reasoning-0.1.1.dist-info/RECORD
