Metadata-Version: 2.4
Name: axis-reasoning
Version: 0.1.1
Summary: AXIS Reasoning - Internal reasoning and orchestration logic
Author-email: Emily Veiga <emily@lumpi.ai>
License: Proprietary
Project-URL: Homepage, https://github.com/emilyveigaai/axis-reasoning
Project-URL: Repository, https://github.com/emilyveigaai/axis-reasoning
Project-URL: Issues, https://github.com/emilyveigaai/axis-reasoning/issues
Requires-Python: >=3.10
Requires-Dist: axis-sdk>=0.3.1
Requires-Dist: lumpi-axis-registry>=0.1.1
Requires-Dist: anthropic>=0.25.0
Requires-Dist: google-genai>=0.3.0
Requires-Dist: pydantic>=2.0.0
Requires-Dist: python-dotenv>=1.0.0
Provides-Extra: dev
Requires-Dist: pytest>=7.0.0; extra == "dev"
Requires-Dist: pytest-cov>=4.0.0; extra == "dev"
Requires-Dist: black>=23.0.0; extra == "dev"
Requires-Dist: ruff>=0.1.0; extra == "dev"
Requires-Dist: mypy>=1.0.0; extra == "dev"
